httpie_lambda.py
httpie_lambda-1.0.dist-info/LICENSE
httpie_lambda-1.0.dist-info/METADATA
httpie_lambda-1.0.dist-info/WHEEL
httpie_lambda-1.0.dist-info/entry_points.txt
httpie_lambda-1.0.dist-info/top_level.txt
httpie_lambda-1.0.dist-info/RECORD
