Metadata-Version: 2.1
Name: httpie-lambda
Version: 1.0
Summary: AWS Lambda invoke transport plugin for HTTPie
Home-page: https://github.com/IlyaSukhanov/httpie-lambda
Author: Ilya Sukhanov
Author-email: ilya@sukhanov.net
License: MIT license
Keywords: HTTPie
Platform: UNKNOWN
Classifier: Intended Audience :: Developers
Classifier: License :: OSI Approved :: MIT License
Classifier: Natural Language :: English
Classifier: Programming Language :: Python :: 3
Classifier: Programming Language :: Python :: 3.9
License-File: LICENSE
Requires-Dist: lambda-requests (>=1.4)
Requires-Dist: httpie (>=2.5.0)
Provides-Extra: testing
Requires-Dist: pip (~=20.3) ; extra == 'testing'
Requires-Dist: flake8 ; extra == 'testing'
Requires-Dist: tox ; extra == 'testing'
Requires-Dist: coverage ; extra == 'testing'
Requires-Dist: pytest ; extra == 'testing'
Requires-Dist: pyflakes ; extra == 'testing'
Requires-Dist: pytest-cov ; extra == 'testing'
Requires-Dist: bandit ; extra == 'testing'
Requires-Dist: black (~=21.5b1) ; extra == 'testing'
Requires-Dist: isort ; extra == 'testing'
Requires-Dist: wheel ; extra == 'testing'
Requires-Dist: twine ; extra == 'testing'
